nairaland/__init__.py
nairaland/browser.py
nairaland/nairaland.py
nairaland/user.py
nairaland-1.0.3.dist-info/LICENSE
nairaland-1.0.3.dist-info/METADATA
nairaland-1.0.3.dist-info/WHEEL
nairaland-1.0.3.dist-info/top_level.txt
nairaland-1.0.3.dist-info/RECORD
