Metadata-Version: 2.1
Name: nairaland
Version: 1.0.3
Summary: Fetches and parses data from Nairaland.
Home-page: https://github.com/djunehor/pynairaland
Author: Zacchaeus Bolaji
Author-email: djunehor@gmail.com
License: UNKNOWN
Platform: UNKNOWN
Requires-Dist: beautifulsoup4 (==4.4.0)
Requires-Dist: feedparser (==5.2.1)
Requires-Dist: requests (==2.21.0)
Requires-Dist: dateparser
Requires-Dist: selenium
Requires-Dist: lxml
